{"cameraMode":{"drawMode":0,"name":"Shaded","section":"Shading Mode"},"sceneLighting":true,"audioPlay":false,"sceneViewState":{"showFog":true,"showMaterialUpdate":false,"showSkybox":true,"showFlares":true,"showImageEffects":true,"showParticleSystems":true},"in2DMode":false,"pivot":{"x":4.0352983474731449,"y":2.1358118057250978,"z":-5.53003454208374},"rotation":{"x":-0.1718158721923828,"y":0.4561270475387573,"z":-0.09023628383874893,"w":-0.8684963583946228},"size":6.529865264892578,"orthographic":false}